ga_vqc/Distance.py
ga_vqc/GA_ABC.py
ga_vqc/GA_Manager.py
ga_vqc/GA_Support.py
ga_vqc/Genes.py
ga_vqc/VQC_ABC.py
ga_vqc/__init__.py
ga_vqc/simple_Config.py
ga_vqc/simple_Individual.py
ga_vqc/simple_Model.py
ga_vqc-1.0.14.dist-info/LICENSE
ga_vqc-1.0.14.dist-info/METADATA
ga_vqc-1.0.14.dist-info/WHEEL
ga_vqc-1.0.14.dist-info/top_level.txt
ga_vqc-1.0.14.dist-info/RECORD
