Metadata-Version: 2.1
Name: ga_vqc
Version: 1.0.14
Summary: Genetic Algorithm for VQC ansatz search.
Home-page: https://github.com/tcoulvert/GA_Ansatz_Search
Author: Thomas Sievert
Author-email: 63161166+tcoulvert@users.noreply.github.com
Classifier: Programming Language :: Python :: 3
Classifier: License :: OSI Approved :: MIT License
Classifier: Operating System :: OS Independent
License-File: LICENSE
Requires-Dist: matplotlib >=2.2.5
Requires-Dist: numpy >=1.23
Requires-Dist: pandas >=1.5
Requires-Dist: scikit-learn >=1.2
Requires-Dist: pennylane >=0.29
Requires-Dist: pennylane-qulacs >=0.32
Requires-Dist: qulacs-gpu >=0.3
Provides-Extra: dev
Requires-Dist: pytest >=3.7 ; extra == 'dev'
Requires-Dist: check-manifest >=0.47 ; extra == 'dev'
